simplify_polyline/__init__.py
simplify_polyline/helpers.py
simplify_polyline/py.typed
simplify_polyline/simplifiers.py
simplify_polyline/type_hints.py
simplify_polyline-0.1.0.dist-info/METADATA
simplify_polyline-0.1.0.dist-info/WHEEL
simplify_polyline-0.1.0.dist-info/top_level.txt
simplify_polyline-0.1.0.dist-info/RECORD
