Metadata-Version: 2.1
Name: simplify_polyline
Version: 0.1.0
Summary: Simplify an open or closed polyline
Author-email: Shay Hill <shay_public@hotmail.com>
License: MIT
Requires-Python: >=3.9
Requires-Dist: numpy
Provides-Extra: dev
Requires-Dist: commitizen ; extra == 'dev'
Requires-Dist: pre-commit ; extra == 'dev'
Requires-Dist: pytest ; extra == 'dev'
Requires-Dist: tox ; extra == 'dev'
